jaraco/stream/__init__.py
jaraco/stream/buffer.py
jaraco/stream/gzip.py
jaraco/stream/test_gzip.py
jaraco.stream-3.0.4.dist-info/LICENSE
jaraco.stream-3.0.4.dist-info/METADATA
jaraco.stream-3.0.4.dist-info/WHEEL
jaraco.stream-3.0.4.dist-info/top_level.txt
jaraco.stream-3.0.4.dist-info/RECORD
